{"stats":{"minecraft:custom":{"minecraft:time_since_rest":11607,"minecraft:interact_with_smithing_table":1,"minecraft:sprint_one_cm":21,"minecraft:play_time":11607,"minecraft:walk_one_cm":11546,"minecraft:interact_with_anvil":1,"minecraft:jump":18,"minecraft:leave_game":2,"minecraft:walk_on_water_one_cm":332,"minecraft:time_since_death":11607,"minecraft:total_world_time":22490,"minecraft:interact_with_crafting_table":1,"minecraft:fly_one_cm":5190},"minecraft:picked_up":{"isleofberk:belzium":5,"minecraft:oak_log":2},"minecraft:used":{"minecraft:diamond_pickaxe":2,"isleofberk:belzium_pickaxe":1,"isleofberk:gronckle_iron_pickaxe":1,"isleofberk:gronckle_iron_block":7,"minecraft:anvil":1,"minecraft:crafting_table":1,"minecraft:smithing_table":1,"isleofberk:raw_gronckle_iron_block":4,"minecraft:golden_pickaxe":1,"isleofberk:belzium_ore":18},"minecraft:mined":{"minecraft:oak_log":2,"isleofberk:belzium_ore":3,"minecraft:oak_leaves":2}},"DataVersion":2975}