{"stats":{"minecraft:used":{"minecraft:diamond_pickaxe":2,"isleofberk:gronckle_iron_block":7,"isleofberk:raw_gronckle_iron_block":4,"minecraft:golden_pickaxe":1,"isleofberk:belzium_ore":18},"minecraft:mined":{"minecraft:oak_log":2,"isleofberk:belzium_ore":1,"minecraft:oak_leaves":2},"minecraft:custom":{"minecraft:time_since_rest":6881,"minecraft:leave_game":2,"minecraft:play_time":6881,"minecraft:time_since_death":6881,"minecraft:sprint_one_cm":21,"minecraft:walk_on_water_one_cm":332,"minecraft:walk_one_cm":9497,"minecraft:total_world_time":10112,"minecraft:fly_one_cm":3058,"minecraft:jump":13},"minecraft:picked_up":{"isleofberk:belzium":1,"minecraft:oak_log":2}},"DataVersion":2975}