{"stats":{"minecraft:mined":{"minecraft:oak_log":2,"minecraft:stone":1,"isleofberk:belzium_ore":16,"minecraft:oak_leaves":2},"minecraft:dropped":{"minecraft:stone":62},"minecraft:used":{"minecraft:diamond_pickaxe":2,"isleofberk:speed_stinger_spawn_egg":2,"isleofberk:gronckle_iron_block":7,"minecraft:anvil":1,"minecraft:crafting_table":1,"minecraft:smithing_table":1,"isleofberk:gronckle_spawn_egg":1,"isleofberk:monstrous_nightmare_egg":1,"minecraft:stone":1,"isleofberk:raw_gronckle_iron_block":4,"minecraft:golden_pickaxe":15,"isleofberk:belzium_ore":18},"minecraft:picked_up":{"isleofberk:belzium":25,"isleofberk:monstrous_nightmare_egg":1,"minecraft:stone":126,"isleofberk:raw_gronckle_iron":1,"minecraft:oak_log":2,"minecraft:cobblestone":1},"minecraft:custom":{"minecraft:time_since_rest":17778,"minecraft:interact_with_smithing_table":1,"minecraft:sprint_one_cm":21,"minecraft:play_time":17778,"minecraft:walk_one_cm":18830,"minecraft:sneak_time":19,"minecraft:interact_with_anvil":1,"minecraft:drop":1,"minecraft:jump":24,"minecraft:damage_dealt":0,"minecraft:leave_game":5,"minecraft:walk_on_water_one_cm":332,"minecraft:time_since_death":17778,"minecraft:total_world_time":30219,"minecraft:interact_with_crafting_table":1,"minecraft:fly_one_cm":5217}},"DataVersion":2975}